linkedtext/__init__.py
linkedtext/cli.py
linkedtext/exceptions.py
linkedtext/linkedtext.py
linkedtext/utils.py
linkedtext-0.1.3.dist-info/METADATA
linkedtext-0.1.3.dist-info/WHEEL
linkedtext-0.1.3.dist-info/entry_points.txt
linkedtext-0.1.3.dist-info/RECORD
