Metadata-Version: 2.1
Name: linkedtext
Version: 0.1.3
Summary: Easily generate links and table of contents in Markdown files.
Home-page: https://github.com/kurotom/linkedText
License: LGPL-3.0-or-later
Keywords: text,links,index
Author: kurotom
Author-email: 55354389+kurotom@users.noreply.github.com
Requires-Python: >=3.7,<4.0
Classifier: License :: OSI Approved :: GNU General Public License v3 or later (GPLv3+)
Classifier: License :: OSI Approved :: GNU Lesser General Public License v3 or later (LGPLv3+)
Classifier: Operating System :: OS Independent
Classifier: Programming Language :: Python :: 3
Classifier: Programming Language :: Python :: 3.7
Classifier: Programming Language :: Python :: 3.8
Classifier: Programming Language :: Python :: 3.9
Classifier: Programming Language :: Python :: 3.10
Classifier: Programming Language :: Python :: 3.11
Classifier: Topic :: Terminals
Classifier: Topic :: Text Processing
Classifier: Topic :: Text Processing :: Indexing
Classifier: Topic :: Text Processing :: Markup :: Markdown
Classifier: Topic :: Utilities
Project-URL: Bug Tracker, https://github.com/kurotom/linkedText/issues
Project-URL: Repository, https://github.com/kurotom/linkedText
